<?xml version="1.0" encoding="utf-8" ?>
<dwsync>
<file name="index.html" server="dusitftp.dusit.ac.th/public_html/" local="131401676553540459" remote="131293392000000000" Dst="0" />
<file name="timetable.php" server="dusitftp.dusit.ac.th/public_html/" local="131401676553720930" remote="131293392000000000" Dst="0" />
<file name="welcome_message.php" server="dusitftp.dusit.ac.th/public_html/" local="131401676553811173" remote="131293392000000000" Dst="0" />
<file name="grade.php" server="dusitftp.dusit.ac.th/public_html/" local="131401676553630693" remote="131293392000000000" Dst="0" />
<file name="grade.php" server="dusitftp.dusit.ac.th/public_html/eprofile_dev/" local="131401676553630693" remote="131405677200000000" Dst="0" />
<file name="index.html" server="dusitftp.dusit.ac.th/public_html/eprofile_dev/" local="131401676553540459" remote="131405677200000000" Dst="0" />
<file name="timetable.php" server="dusitftp.dusit.ac.th/public_html/eprofile_dev/" local="131401676553720930" remote="131405677200000000" Dst="0" />
<file name="welcome_message.php" server="dusitftp.dusit.ac.th/public_html/eprofile_dev/" local="131401676553811173" remote="131405677200000000" Dst="0" />
</dwsync>