<?xml version="1.0" encoding="utf-8" ?>
<dwsync>
<file name="bootstrap-theme.min.css" server="dusitftp.dusit.ac.th/public_html/" local="131401676353031762" remote="131111748000000000" Dst="0" />
<file name="bootstrap-theme.css" server="dusitftp.dusit.ac.th/public_html/" local="131401676353484989" remote="131111748000000000" Dst="0" />
<file name="bootstrap.min.css" server="dusitftp.dusit.ac.th/public_html/" local="131401676354237583" remote="131111748000000000" Dst="0" />
<file name="normalize.css" server="dusitftp.dusit.ac.th/public_html/" local="131401676355962173" remote="131111748000000000" Dst="0" />
<file name="reset.css" server="dusitftp.dusit.ac.th/public_html/" local="131401676978681376" remote="131111748000000000" Dst="0" />
<file name="style.css" server="dusitftp.dusit.ac.th/public_html/" local="131401676356874590" remote="131111748000000000" Dst="0" />
<file name="bootstrap.css" server="dusitftp.dusit.ac.th/public_html/" local="131401676355801744" remote="131111748000000000" Dst="0" />
<file name="bootstrap-theme.css" server="dusitftp.dusit.ac.th/public_html/eprofile_dev/" local="131401676353484989" remote="131405676600000000" Dst="0" />
<file name="bootstrap-theme.min.css" server="dusitftp.dusit.ac.th/public_html/eprofile_dev/" local="131401676353031762" remote="131405676600000000" Dst="0" />
<file name="bootstrap.css" server="dusitftp.dusit.ac.th/public_html/eprofile_dev/" local="131401676355801744" remote="131405676600000000" Dst="0" />
<file name="bootstrap.min.css" server="dusitftp.dusit.ac.th/public_html/eprofile_dev/" local="131401676354237583" remote="131405676600000000" Dst="0" />
<file name="normalize.css" server="dusitftp.dusit.ac.th/public_html/eprofile_dev/" local="131401676355962173" remote="131405676600000000" Dst="0" />
<file name="reset.css" server="dusitftp.dusit.ac.th/public_html/eprofile_dev/" local="131401676978681376" remote="131405676600000000" Dst="0" />
<file name="style.css" server="dusitftp.dusit.ac.th/public_html/eprofile_dev/" local="131401676356874590" remote="131405676600000000" Dst="0" />
</dwsync>