<?xml version="1.0" encoding="utf-8" ?>
<dwsync>
<file name="jquery.effects.blind.min.js" server="dusitftp.dusit.ac.th/public_html/" local="131401676773568322" remote="131111748000000000" Dst="0" />
<file name="jquery.effects.bounce.min.js" server="dusitftp.dusit.ac.th/public_html/" local="131401676773688647" remote="131111748000000000" Dst="0" />
<file name="jquery.effects.clip.min.js" server="dusitftp.dusit.ac.th/public_html/" local="131401676773798938" remote="131111748000000000" Dst="0" />
<file name="jquery.effects.core.min.js" server="dusitftp.dusit.ac.th/public_html/" local="131401676773999471" remote="131111748000000000" Dst="0" />
<file name="jquery.effects.drop.min.js" server="dusitftp.dusit.ac.th/public_html/" local="131401676774129811" remote="131111748000000000" Dst="0" />
<file name="jquery.effects.explode.min.js" server="dusitftp.dusit.ac.th/public_html/" local="131401676774189971" remote="131111748000000000" Dst="0" />
<file name="jquery.effects.fade.min.js" server="dusitftp.dusit.ac.th/public_html/" local="131401676774330344" remote="131111748000000000" Dst="0" />
<file name="jquery.effects.fold.min.js" server="dusitftp.dusit.ac.th/public_html/" local="131401676774440637" remote="131111748000000000" Dst="0" />
<file name="jquery.effects.highlight.min.js" server="dusitftp.dusit.ac.th/public_html/" local="131401676774480747" remote="131111748000000000" Dst="0" />
<file name="jquery.effects.pulsate.min.js" server="dusitftp.dusit.ac.th/public_html/" local="131401676774631156" remote="131111748000000000" Dst="0" />
<file name="jquery.effects.shake.min.js" server="dusitftp.dusit.ac.th/public_html/" local="131401676774731410" remote="131111748000000000" Dst="0" />
<file name="jquery.effects.scale.min.js" server="dusitftp.dusit.ac.th/public_html/" local="131401676774851736" remote="131111748000000000" Dst="0" />
<file name="jquery.effects.slide.min.js" server="dusitftp.dusit.ac.th/public_html/" local="131401676775022183" remote="131111748000000000" Dst="0" />
<file name="jquery.effects.transfer.min.js" server="dusitftp.dusit.ac.th/public_html/" local="131401676775122456" remote="131111748000000000" Dst="0" />
<file name="jquery.ui.accordion.min.js" server="dusitftp.dusit.ac.th/public_html/" local="131401676775323010" remote="131111748000000000" Dst="0" />
<file name="jquery.ui.core.min.js" server="dusitftp.dusit.ac.th/public_html/" local="131401676775714022" remote="131111748000000000" Dst="0" />
<file name="jquery.ui.autocomplete.min.js" server="dusitftp.dusit.ac.th/public_html/" local="131401676776004795" remote="131111748000000000" Dst="0" />
<file name="jquery.ui.button.min.js" server="dusitftp.dusit.ac.th/public_html/" local="131401676776195310" remote="131111748000000000" Dst="0" />
<file name="jquery.ui.dialog.min.js" server="dusitftp.dusit.ac.th/public_html/" local="131401676776596518" remote="131111748000000000" Dst="0" />
<file name="jquery.ui.draggable.min.js" server="dusitftp.dusit.ac.th/public_html/" local="131401676776796903" remote="131111748000000000" Dst="0" />
<file name="jquery.ui.datepicker.min.js" server="dusitftp.dusit.ac.th/public_html/" local="131401676777017496" remote="131111748000000000" Dst="0" />
<file name="jquery.ui.droppable.min.js" server="dusitftp.dusit.ac.th/public_html/" local="131401676777268162" remote="131111748000000000" Dst="0" />
<file name="jquery.ui.mouse.min.js" server="dusitftp.dusit.ac.th/public_html/" local="131401676777468701" remote="131111748000000000" Dst="0" />
<file name="jquery.ui.position.min.js" server="dusitftp.dusit.ac.th/public_html/" local="131401676777599117" remote="131111748000000000" Dst="0" />
<file name="jquery.ui.progressbar.min.js" server="dusitftp.dusit.ac.th/public_html/" local="131401676777799623" remote="131111748000000000" Dst="0" />
<file name="jquery.ui.selectable.min.js" server="dusitftp.dusit.ac.th/public_html/" local="131401676777949956" remote="131111748000000000" Dst="0" />
<file name="jquery.ui.resizable.min.js" server="dusitftp.dusit.ac.th/public_html/" local="131401676778200863" remote="131111748000000000" Dst="0" />
<file name="jquery.ui.slider.min.js" server="dusitftp.dusit.ac.th/public_html/" local="131401676778682214" remote="131111748000000000" Dst="0" />
<file name="jquery.ui.tabs.min.js" server="dusitftp.dusit.ac.th/public_html/" local="131401676778962660" remote="131111748000000000" Dst="0" />
<file name="jquery.ui.sortable.min.js" server="dusitftp.dusit.ac.th/public_html/" local="131401676779213329" remote="131111748000000000" Dst="0" />
<file name="jquery.ui.widget.min.js" server="dusitftp.dusit.ac.th/public_html/" local="131401676779474037" remote="131111748000000000" Dst="0" />
</dwsync>